{
    "createMessageModalHeader": [
        "Insert the details of the new message",
        "Insira os detalhes da nova mensagem"
    ],
    "savingCredential": [
        "Saving credential...",
        "A gravar credencial..."
    ],
    "receiver": [
        "Receiver",
        "Destinatário"
    ],
    "ttl": [
        "Time before destruction",
        "Tempo de vida"
    ],
    "message": [
        "Message",
        "Mensagem"
    ],
    "youCanAccess": [
        "You can access the message through the ",
        "Pode aceder à credencial através da seguinte "
    ],
    "link": [
        " link.",
        " ligação."
    ],
    "chooseLocation": [
        "Choose location",
        "Escolher pasta"
    ],
    "send": [
        "Send",
        "Enviar"
    ],
    "emailSent": [
        "An email has been dispatched to the receiver.",
        "Foi enviado um email para o destinatário."
    ],
    "receiverNotMandatory": [
        "The sender must be a valid email or nothing at all to only generate a link...",
        "O destinatário tem de ser um e-mail válido, ou nada para apenas gerar um link..."
    ],
    "messageSent": [
        "Message sent successfuly",
        "Mensagem enviada com sucesso"
    ],
    "messageSaved": [
        "Message saved successfuly",
        "Mensgem guardada com sucesso"
    ],
    "messageDeleted": [
        "Message deleted successfuly",
        "Mensagem eliminada com sucesso"
    ]
}